pytekla/__about__.py
pytekla/__init__.py
pytekla/data_manager.py
pytekla/wrappers.py
pytekla/config/__init__.py
pytekla/config/config.json
pytekla/config/config.py
pytekla/coreutils/__init__.py
pytekla/coreutils/collections.py
pytekla/coreutils/names.py
pytekla/coreutils/properties.py
pytekla-0.1.0b0.dist-info/METADATA
pytekla-0.1.0b0.dist-info/WHEEL
pytekla-0.1.0b0.dist-info/licenses/LICENSE
pytekla-0.1.0b0.dist-info/RECORD
